[
  {
    "description": "",
    "elements": [
      {
        "description": "",
        "id": "web-content-creation;create-a-web-content-with-admin-user",
        "keyword": "Scenario",
        "line": 6,
        "name": "Create a web content with Admin user",
        "steps": [
          {
            "keyword": "Before",
            "hidden": true,
            "result": {
              "status": "passed",
              "duration": 433915799
            }
          },
          {
            "arguments": [],
            "keyword": "Given ",
            "line": 4,
            "name": "I am logged in as Admin",
            "match": {
              "location": "test\\commonstep.spec.ts:7"
            },
            "result": {
              "status": "passed",
              "duration": 5193007800
            }
          },
          {
            "arguments": [],
            "keyword": "Then ",
            "line": 7,
            "name": "I should see the product menu",
            "match": {
              "location": "test\\webcontent.spec.ts:6"
            },
            "result": {
              "status": "passed",
              "duration": 12945567600
            }
          },
          {
            "arguments": [],
            "keyword": "Then ",
            "line": 8,
            "name": "I should able to see Content & Data menu",
            "match": {
              "location": "test\\webcontent.spec.ts:11"
            },
            "result": {
              "status": "passed",
              "duration": 1250904399
            }
          },
          {
            "arguments": [],
            "keyword": "When ",
            "line": 9,
            "name": "I click on Content & Data menu",
            "match": {
              "location": "test\\webcontent.spec.ts:15"
            },
            "result": {
              "status": "passed",
              "duration": 2737508899
            }
          },
          {
            "arguments": [],
            "keyword": "Then ",
            "line": 10,
            "name": "I should able to see Web content folder",
            "match": {
              "location": "test\\webcontent.spec.ts:19"
            },
            "result": {
              "status": "passed",
              "duration": 2195259500
            }
          },
          {
            "arguments": [],
            "keyword": "Then ",
            "line": 11,
            "name": "I click on Web content folder",
            "result": {
              "status": "undefined",
              "duration": 0
            }
          },
          {
            "arguments": [],
            "keyword": "Then ",
            "line": 12,
            "name": "I click on New",
            "match": {
              "location": "test\\webcontent.spec.ts:23"
            },
            "result": {
              "status": "skipped",
              "duration": 0
            }
          },
          {
            "arguments": [],
            "keyword": "Then ",
            "line": 13,
            "name": "I click on menu item Basic Web content option",
            "match": {
              "location": "test\\webcontent.spec.ts:27"
            },
            "result": {
              "status": "skipped",
              "duration": 0
            }
          },
          {
            "arguments": [],
            "keyword": "Then ",
            "line": 14,
            "name": "I am able to view a Form",
            "match": {
              "location": "test\\webcontent.spec.ts:30"
            },
            "result": {
              "status": "skipped",
              "duration": 0
            }
          },
          {
            "keyword": "After",
            "hidden": true,
            "result": {
              "status": "passed",
              "duration": 18503613900
            }
          }
        ],
        "tags": [],
        "type": "scenario"
      }
    ],
    "id": "web-content-creation",
    "line": 1,
    "keyword": "Feature",
    "name": "Web Content Creation",
    "tags": [],
    "uri": "features\\webcontent.feature"
  }
]